hed/__init__.py
hed/__main__.py
hed/cli.py
hed/config.py
hed/git.py
hed/operations.py
hed/py.typed
hed-1.1.0.dist-info/METADATA
hed-1.1.0.dist-info/WHEEL
hed-1.1.0.dist-info/entry_points.txt
hed-1.1.0.dist-info/licenses/LICENSE
hed-1.1.0.dist-info/RECORD
