Metadata-Version: 2.4
Name: hed
Version: 1.1.0
Summary: Extract release notes from markdown changelog
Project-URL: Repository, https://github.com/tahv/hed
Author: Thibaud Gambier
License-Expression: MIT
License-File: LICENSE
Classifier: Development Status :: 5 - Production/Stable
Classifier: Intended Audience :: Developers
Classifier: Operating System :: OS Independent
Classifier: Programming Language :: Python :: 3
Classifier: Topic :: Software Development
Requires-Python: >=3.11
Requires-Dist: cyclopts>=4.5.0
Requires-Dist: marko>=2.2.2
Requires-Dist: pygit2>=1.18.2
Requires-Dist: rich>=14.2.0
Requires-Dist: typing-extensions>=4.15.0
